setup.py
event_bus/__init__.py
event_bus/bus.py
event_bus/exceptions.py
event_bus_py2.egg-info/PKG-INFO
event_bus_py2.egg-info/SOURCES.txt
event_bus_py2.egg-info/dependency_links.txt
event_bus_py2.egg-info/top_level.txt